aprs_backend/APRSHealth.plug
aprs_backend/APRSHelp.plug
aprs_backend/APRSWebserver.plug
aprs_backend/__init__.py
aprs_backend/aprs.plug
aprs_backend/aprs.py
aprs_backend/aprs_core_plugins.py
aprs_backend/clients/__init__.py
aprs_backend/clients/_base.py
aprs_backend/clients/aprs_registry.py
aprs_backend/clients/aprsis.py
aprs_backend/clients/beacon.py
aprs_backend/clients/kiss.py
aprs_backend/exceptions/__init__.py
aprs_backend/exceptions/base.py
aprs_backend/exceptions/client/__init__.py
aprs_backend/exceptions/client/aprsis.py
aprs_backend/exceptions/packets/__init__.py
aprs_backend/exceptions/packets/parser.py
aprs_backend/exceptions/processor.py
aprs_backend/message.py
aprs_backend/packets/__init__.py
aprs_backend/packets/parser.py
aprs_backend/person.py
aprs_backend/plugins/__init__.py
aprs_backend/plugins/health.py
aprs_backend/plugins/help.py
aprs_backend/plugins/web.py
aprs_backend/room.py
aprs_backend/utils/__init__.py
aprs_backend/utils/counter.py
aprs_backend/utils/datetime.py
aprs_backend/utils/plugins.py
aprs_backend/utils/position.py
aprs_backend/version.py
err_aprs_backend-0.5.1.dist-info/LICENSE
err_aprs_backend-0.5.1.dist-info/METADATA
err_aprs_backend-0.5.1.dist-info/WHEEL
err_aprs_backend-0.5.1.dist-info/entry_points.txt
err_aprs_backend-0.5.1.dist-info/RECORD
