Metadata-Version: 2.1
Name: err-aprs-backend
Version: 0.5.1
Summary: Errbot APRS backend plugin
License: MIT
Author: Andrew Herrington
Author-email: andrew.the.techie@gmail.com
Requires-Python: >=3.11,<4.0
Classifier: License :: OSI Approved :: MIT License
Classifier: Programming Language :: Python :: 3
Classifier: Programming Language :: Python :: 3.11
Classifier: Programming Language :: Python :: 3.12
Requires-Dist: aprslib (>=0.7.2,<0.8.0)
Requires-Dist: better-profanity (>=0.7.0,<0.8.0)
Requires-Dist: dataclasses-json (>=0.6.4,<0.7.0)
Requires-Dist: expiringdict (>=1.2.2,<2.0.0)
Requires-Dist: httpx (>=0.27.0,<0.28.0)
